mkdocs_macros_adr_summary/__init__.py
mkdocs_macros_adr_summary/factory.py
mkdocs_macros_adr_summary/interfaces.py
mkdocs_macros_adr_summary/plugin.py
mkdocs_macros_adr_summary/py.typed
mkdocs_macros_adr_summary/renderer.py
mkdocs_macros_adr_summary/template.jinja
mkdocs_macros_adr_summary/version.py
mkdocs_macros_adr_summary/parser/__init__.py
mkdocs_macros_adr_summary/parser/base.py
mkdocs_macros_adr_summary/parser/exceptions.py
mkdocs_macros_adr_summary/parser/madr2.py
mkdocs_macros_adr_summary/parser/madr3.py
mkdocs_macros_adr_summary/parser/madr4.py
mkdocs_macros_adr_summary/parser/nygard.py
mkdocs_macros_adr_summary/parser/types.py
mkdocs_macros_adr_summary-1.3.0.dist-info/METADATA
mkdocs_macros_adr_summary-1.3.0.dist-info/WHEEL
mkdocs_macros_adr_summary-1.3.0.dist-info/licenses/LICENSE
mkdocs_macros_adr_summary-1.3.0.dist-info/RECORD
