Metadata-Version: 2.4
Name: mkdocs-macros-adr-summary
Version: 1.3.0
Summary: A plugin to generate a summary of a ADR directory
Project-URL: Homepage, https://febus982.github.io/mkdocs-macros-adr-summary
Project-URL: Repository, https://github.com/febus982/mkdocs-macros-adr-summary
Author-email: Federico Busetti <729029+febus982@users.noreply.github.com>
License-Expression: MIT
License-File: LICENSE
Keywords: adr,architecture-decision-records,mkdocs,mkdocs-macro,mkdocs-macro-plugin,mkdocs-plugin,nygard
Classifier: Development Status :: 4 - Beta
Classifier: Framework :: MkDocs
Classifier: Intended Audience :: Developers
Classifier: License :: OSI Approved :: MIT License
Classifier: Natural Language :: English
Classifier: Operating System :: OS Independent
Classifier: Programming Language :: Python
Classifier: Programming Language :: Python :: 3
Classifier: Programming Language :: Python :: 3 :: Only
Classifier: Programming Language :: Python :: 3.9
Classifier: Programming Language :: Python :: 3.10
Classifier: Programming Language :: Python :: 3.11
Classifier: Programming Language :: Python :: 3.12
Classifier: Programming Language :: Python :: 3.13
Classifier: Programming Language :: Python :: 3.14
Classifier: Topic :: Documentation
Classifier: Topic :: Software Development
Classifier: Topic :: Software Development :: Documentation
Classifier: Topic :: Software Development :: Libraries
Classifier: Topic :: Software Development :: Libraries :: Python Modules
Classifier: Typing :: Typed
Requires-Python: <3.15,>=3.9
Requires-Dist: mistune<3.1,>=3.0.2
Requires-Dist: mkdocs-macros-plugin<2,>=1.0.5
Requires-Dist: mkdocs<2,>=1.4.3
Requires-Dist: pyyaml<7,>=6.0.1
